dotnetcore2/NOTICE.txt
dotnetcore2/__init__.py
dotnetcore2/runtime.py
dotnetcore2/bin/LICENSE.txt
dotnetcore2/bin/ThirdPartyNotices.txt
dotnetcore2/bin/dotnet.exe
dotnetcore2/bin/host/fxr/2.1.30/hostfxr.dll
dotnetcore2/bin/shared/Microsoft.NETCore.App/2.1.30/Microsoft.CSharp.dll
dotnetcore2/bin/shared/Microsoft.NETCore.App/2.1.30/Microsoft.DiaSymReader.Native.amd64.dll
dotnetcore2/bin/shared/Microsoft.NETCore.App/2.1.30/Microsoft.NETCore.App.deps.json
dotnetcore2/bin/shared/Microsoft.NETCore.App/2.1.30/Microsoft.VisualBasic.dll
dotnetcore2/bin/shared/Microsoft.NETCore.App/2.1.30/Microsoft.Win32.Primitives.dll
dotnetcore2/bin/shared/Microsoft.NETCore.App/2.1.30/Microsoft.Win32.Registry.dll
dotnetcore2/bin/shared/Microsoft.NETCore.App/2.1.30/SOS.NETCore.dll
dotnetcore2/bin/shared/Microsoft.NETCore.App/2.1.30/System.AppContext.dll
dotnetcore2/bin/shared/Microsoft.NETCore.App/2.1.30/System.Buffers.dll
dotnetcore2/bin/shared/Microsoft.NETCore.App/2.1.30/System.Collections.Concurrent.dll
dotnetcore2/bin/shared/Microsoft.NETCore.App/2.1.30/System.Collections.Immutable.dll
dotnetcore2/bin/shared/Microsoft.NETCore.App/2.1.30/System.Collections.NonGeneric.dll
dotnetcore2/bin/shared/Microsoft.NETCore.App/2.1.30/System.Collections.Specialized.dll
dotnetcore2/bin/shared/Microsoft.NETCore.App/2.1.30/System.Collections.dll
dotnetcore2/bin/shared/Microsoft.NETCore.App/2.1.30/System.ComponentModel.Annotations.dll
dotnetcore2/bin/shared/Microsoft.NETCore.App/2.1.30/System.ComponentModel.DataAnnotations.dll
dotnetcore2/bin/shared/Microsoft.NETCore.App/2.1.30/System.ComponentModel.EventBasedAsync.dll
dotnetcore2/bin/shared/Microsoft.NETCore.App/2.1.30/System.ComponentModel.Primitives.dll
dotnetcore2/bin/shared/Microsoft.NETCore.App/2.1.30/System.ComponentModel.TypeConverter.dll
dotnetcore2/bin/shared/Microsoft.NETCore.App/2.1.30/System.ComponentModel.dll
dotnetcore2/bin/shared/Microsoft.NETCore.App/2.1.30/System.Configuration.dll
dotnetcore2-2.1.23.dist-info/METADATA
dotnetcore2-2.1.23.dist-info/WHEEL
dotnetcore2-2.1.23.dist-info/top_level.txt
dotnetcore2-2.1.23.dist-info/RECORD
