Metadata-Version: 2.1
Name: dotnetcore2
Version: 2.1.23
Summary: .Net Core 2.1 runtime
Home-page: https://github.com/dotnet/core
Author: Microsoft Corporation
Author-email: 
License: UNKNOWN
Platform: UNKNOWN
Classifier: Development Status :: 5 - Production/Stable
Classifier: Intended Audience :: Developers
Classifier: License :: OSI Approved :: MIT License
Requires-Dist: distro (>=1.2.0)
